muxes/memmux.v
module memmux (
    input [15:0] data_from_mem, alu_result,
    input memtoreg,
    output reg [15:0] memmuxout
);
always @(*)
begin 
    case (memtoreg) 
    1'b0: memmuxout = alu_result;
    1'b1: memmuxout = data_from_mem;
    endcase
end
endmodule

mem.v
module mem (
    input clk,
    input we,
    input [8:0] address,
    input [15:0] data_in,
    output reg [15:0] data_out
);

reg [15:0] ram [0:255];

always @ (posedge clk)
    begin
        if (we) begin
        $display("%b %b", data_in, address);
            ram[address] <= data_in;
        end
        data_out <= ram[address];
        
    end

endmodule

aluctrl.v
module aluctrl(
    input [2:0] opcode,
    input [3:0] func,
    output reg [2:0] ALU_Code
    );

always@(*)
begin 
    case(opcode)
    3'b000:
    begin    
    case(func)
    4'b0000: begin ALU_Code =3'b000; 
   /* $display("hello"); */ end
    4'b0001: ALU_Code = 3'b001; //sub
    4'b0100: ALU_Code = 3'b100; //and
    4'b0101: ALU_Code = 3'b101; //or
    4'b0110: ALU_Code = 3'b110; //not 
    4'b0111: ALU_Code = 3'b111; //xor
    4'b0011: ALU_Code = 3'b011; //slt
    4'b0010: ALU_Code = 3'b010; //lsl

    endcase 
    end
    3'b001: ALU_Code = 3'b000; //addi
    3'b010: ALU_Code = 3'b001; //subi
    3'b011: ALU_Code = 3'b000; //st
    3'b100: ALU_Code = 3'b000; //ld
    3'b110: ALU_Code = 3'b001; //beq
    endcase

end

endmodule

control.v
module control(
input [2:0] opcode, 
output reg jump, branch, memwrite, regwrite, alusrc, reg_dest, memtoreg );
 always @(*)
 begin 
     case (opcode)
     3'b000:  //d type 
     begin 
     jump = 0;
     branch = 0;
     memwrite = 0;
     regwrite = 1;
     alusrc = 0;
     reg_dest = 0;
     memtoreg = 0;
     end
     3'b001:
    begin 
     jump = 0;
     branch = 0;
     memwrite = 0;
     regwrite = 1;
     alusrc = 1;
     reg_dest = 1;
     memtoreg = 0;
     end
     3'b010: 
     begin 
     jump = 0;
     branch = 0;
     memwrite = 0;
     regwrite = 1;
     alusrc = 1;
     reg_dest = 1;
     memtoreg = 0;
     end
    3'b011: //st
     begin 
     jump = 0;
     branch = 0;
     memwrite = 1;
     regwrite = 0;
     alusrc = 1;
     reg_dest = 1;
     memtoreg = 0;
     end
    3'b100:    //ld
    begin 
    jump = 0;
    branch = 0;
    memwrite = 0;
    regwrite = 1;
    alusrc = 1;
    reg_dest = 1;
    memtoreg = 1;
    end
    3'b101: //jump
    begin  
    jump = 1;
    branch = 0;
    memwrite = 0;
    regwrite = 0;
    alusrc = 0;
    reg_dest = 0;
    memtoreg = 0;
    end
     3'b110: //beq
     begin
    jump = 0;
    branch = 1;
    memwrite = 0;
    regwrite = 0;
    alusrc = 0;
    reg_dest = 0;
    memtoreg = 0;
    end
     endcase
     
 end

endmodule

muxes/alumux.v
module alumux(
    input [6:0] immediate,
    input [15:0] read2,
    input  alusrc,
    output reg [15:0] alumuxout
);
 always @(*)
 begin 
     case (alusrc)
     1'b0: alumuxout =read2;
 
     1'b1: begin alumuxout = {9'b0,immediate};  
  
     end  

     endcase
 end

endmodule

imem.v
module imem(
    input [15:0] pc,
    output [15:0] instruction
);

    reg [15:0] ram [0:255];

    initial $readmemb("code.txt", ram);
    assign instruction = ram[pc];

endmodule

regfile.v
module regfile ( 
input clk, 
input write_en,
input [2:0] rega,regb,wreg,
input [15:0] writedata,
output [15:0] read1, read2
);

reg [15:0] reg8 [7:0];
initial begin
    reg8[0] <= 16'b000000011;
    reg8[1] <= 16'b000000001;
    reg8[2] <= 16'b0;
    reg8[3] <= 16'b0;
    reg8[4] <= 16'b0;
    reg8[5] <= 16'b0;
    reg8[6] <= 16'b0;
    reg8[7] <= 16'b0;
end
always @( posedge clk )
begin 
    if(write_en) begin
    reg8[wreg] <= writedata;
    end
end
assign read1 = reg8[rega];
assign read2 = reg8[regb];

endmodule

regfilemux.v
module regfilemux(
    input reg_dest,
    input [2:0] rt, rd,
    output reg [2:0] reg_result //write register
);

always @(*)
begin
    case (reg_dest)
    1'b0: reg_result = rd; //Sets the write register to rd
    1'b1: reg_result = rt; //Sets the write register to rt
    endcase

end

endmodule

alu.v
module alu(
    input [7:0] A, 
    input [7:0] B,
    input [2:0] ALU_Code,
    output [7:0] ALU_Out, //,
   output Carry,
   output isZero);

reg [7:0] Result;
assign ALU_Out = Result;
always @(*) 
begin 
case(ALU_Code)
    3'b000: Result = A + B; //ADD
    3'b001: Result = A - B; //SUB
    3'b010: Result = A>>1; //LSL
    3'b011: Result = A<<1; //LSR
    3'b100: Result = A & B; //AND
    3'b101: Result = A | B; //A or B
    3'b110: Result = ~(A); //Not
    3'b111: Result = A^B; //Exclusive OR
    //probably should add mult div etc 
    default: Result = A+B;
endcase


end


endmodule

cpu.v
`timescale 1ns/1ns
`include "imem.v"
`include "alu.v"
`include "regfile.v"
`include "control.v"
`include "aluctrl.v"
`include "alumux.v"
`include "regfilemux.v"
`include "mem.v"
`include "memmux.v"
module CPU();

wire [15:0] instruction;
reg clk;
reg [2:0] ctrl;
reg [15:0] pc;
reg [15:0] count;
wire [15:0] res;
wire Carry;
wire isZero;

wire [2:0] rs, rt, rd;
wire [2:0] ALU_Code;
wire [2:0] opcode;
wire [3:0] func;

wire jump, branch, memwrite, regwrite, alusrc, reg_dest, memtoreg;
reg write_en;
reg [15:0] writedata;
wire [15:0] read1, read2;
wire [6:0] immediate;
wire [15:0] alumuxout;
wire [2:0] reg_result;
wire [15:0] mem_out;
wire [15:0] memmuxresult;
wire [12:0] jumpaddr;
//decoding 
assign opcode = instruction[15:13];
assign rs = instruction[12:10];
assign rt = instruction[9:7];
assign rd = instruction[6:4];
assign func = instruction[3:0];
assign immediate = instruction[6:0];
assign jumpaddr = instruction[12:0];


alu alu_test(.A(read1), .B(alumuxout), .ALU_Code(ALU_Code), .ALU_Out(res), .Carry(Carry), .isZero(isZero));
regfilemux regfilemux_test(.reg_dest(reg_dest), .rt(rt), .rd(rd), .reg_result(reg_result));
regfile reg_test(.clk(clk), .write_en(regwrite), .rega(rs), .regb(rt), .wreg(reg_result), .writedata(memmuxresult), .read1(read1), .read2(read2));
imem imem_test(.pc(pc), .instruction(instruction));
alumux alumux_test(.immediate(immediate), .read2(read2), .alusrc(alusrc), .alumuxout(alumuxout));
control control_test(.opcode(opcode), .jump(jump), .branch(branch), .memwrite(memwrite), .regwrite(regwrite), .alusrc(alusrc), .reg_dest(reg_dest), .memtoreg(memtoreg));
aluctrl aluctrl_test(.opcode(opcode),.func(func), .ALU_Code(ALU_Code));
mem mem_test(.clk(clk), .we(memwrite), .address(res), .data_in(read2), .data_out(mem_out));
memmux memmux_test(.data_from_mem(mem_out), .alu_result(res), .memtoreg(memtoreg), .memmuxout(memmuxresult));




always @(posedge clk)
//may have to be negedge 
begin 
     $display("pc : %b instruction : %b branch %b isZero %b", pc, instruction, branch, isZero);
   if(jump  || (branch && isZero)) 
   begin 
    pc = immediate;
   end else begin 
       pc = pc + 1;
   end
   if (instruction == 16'b1111111111111111)
   $finish;
//   count = count +1;

    
end
initial begin
clk = 0;
pc = 0;
count = 0;

$dumpfile("out.vcd");
$dumpvars(0,clk, res);
end
always #20 clk =~ clk;


endmodule

out.vcd
$date
	Sun May 15 10:53:48 2022
$end
$version
	Icarus Verilog
$end
$timescale
	1ns
$end
$scope module CPU $end
$var reg 1 ! clk $end
$upscope $end
$scope module CPU $end
$var wire 16 " res [15:0] $end
$upscope $end
$enddefinitions $end
#0
$dumpvars
b1 "
0!
$end
#20
1!
#40
0!
#60
1!
#80
0!
#100
b1 "
1!
#120
0!
#140
1!
#160
0!
#180
1!
#200
0!
#220
b10 "
1!
#240
0!
#260
b1 "
1!
#280
0!
#300
b0 "
1!
#320
0!
#340
b10 "
1!
#360
0!
#380
b1 "
1!
#400
0!
#420
b10 "
1!
#440
0!
#460
b11 "
1!
#480
0!
#500
b1 "
1!
#520
0!
#540
b0 "
1!
#560
0!
#580
b11 "
1!
#600
0!
#620
b10 "
1!
#640
0!
#660
b11 "
1!
#680
0!
#700
b100 "
1!
#720
0!
#740
b1 "
1!
#760
0!
#780
b0 "
1!
#800
0!
#820
b101 "
1!
#840
0!
#860
b11 "
1!
#880
0!
#900
b101 "
1!
#920
0!
#940
b101 "
1!
#960
0!
#980
b1 "
1!
#1000
0!
#1020
b0 "
1!
#1040
0!
#1060
b1000 "
1!
#1080
0!
#1100
b101 "
1!
#1120
0!
#1140
b1000 "
1!
#1160
0!
#1180
b110 "
1!
#1200
0!
#1220
b1 "
1!
#1240
0!
#1260
b0 "
1!
#1280
0!
#1300
b1101 "
1!
#1320
0!
#1340
b1000 "
1!
#1360
0!
#1380
b1101 "
1!
#1400
0!
#1420
b111 "
1!
#1440
0!
#1460
b1 "
1!
#1480
0!
#1500
b0 "
1!
#1520
0!
#1540
b10101 "
1!
#1560
0!
#1580
b1101 "
1!
#1600
0!
#1620
b10101 "
1!
#1640
0!
#1660
b1000 "
1!
#1680
0!
#1700
b1 "
1!
#1720
0!
#1740
b0 "
1!
#1760
0!
#1780
b100010 "
1!
#1800
0!
#1820
b10101 "
1!
#1840
0!
#1860
b100010 "
1!
#1880
0!
#1900
b1001 "
1!
#1920
0!
#1940
b1 "
1!
#1960
0!
#1980
b0 "
1!
#2000
0!
#2020
b110111 "
1!
#2040
0!
#2060
b100010 "
1!
#2080
0!
#2100
b110111 "
1!
#2120
0!
#2140
b1010 "
1!
#2160
0!
#2180
b0 "
1!
#2200
0!
#2220
b1111111111111111 "
1!
#2240
0!
#2260
b0 "
1!
